COPYING
MANIFEST.in
README
health_imaging_view.xml
setup.py
./__init__.py
./health_imaging.py
./health_imaging_view.xml
./tryton.cfg
./data/health_imaging_sequences.xml
./data/imaging_data.xml
./doc/index.rst
./icons/execute_icon.svg
./icons/imaging_icon.svg
./locale/ar.po
./locale/de.po
./locale/el.po
./locale/es.po
./locale/fr.po
./locale/it_IT.po
./locale/ja_JP.po
./locale/lo.po
./locale/pt_BR.po
./locale/zh_CN.po
./tests/__init__.py
./tests/test_health_imaging.py
./view/imaging_test_form.xml
./view/imaging_test_request_form.xml
./view/imaging_test_request_tree.xml
./view/imaging_test_result_form.xml
./view/imaging_test_result_tree.xml
./view/imaging_test_tree.xml
./view/imaging_test_type_form.xml
./view/imaging_test_type_tree.xml
./view/patient_imaging_test_request_start_form.xml
./wizard/__init__.py
./wizard/wizard_health_imaging.py
data/health_imaging_sequences.xml
data/imaging_data.xml
icons/README
icons/execute_icon.svg
icons/imaging_icon.svg
locale/ar.po
locale/de.po
locale/el.po
locale/es.po
locale/fr.po
locale/it_IT.po
locale/ja_JP.po
locale/lo.po
locale/pt_BR.po
locale/zh_CN.po
trytond_health_imaging.egg-info/PKG-INFO
trytond_health_imaging.egg-info/SOURCES.txt
trytond_health_imaging.egg-info/dependency_links.txt
trytond_health_imaging.egg-info/entry_points.txt
trytond_health_imaging.egg-info/not-zip-safe
trytond_health_imaging.egg-info/requires.txt
trytond_health_imaging.egg-info/top_level.txt
view/imaging_test_form.xml
view/imaging_test_request_form.xml
view/imaging_test_request_tree.xml
view/imaging_test_result_form.xml
view/imaging_test_result_tree.xml
view/imaging_test_tree.xml
view/imaging_test_type_form.xml
view/imaging_test_type_tree.xml
view/patient_imaging_test_request_start_form.xml